lp_mongodb/__init__.py
lp_mongodb/loaders/__init__.py
lp_mongodb/loaders/loader.py
lp_mongodb/storages/__init__.py
lp_mongodb/storages/mongo_storage.py
lp_mongodb-1.2.0.dist-info/LICENSE
lp_mongodb-1.2.0.dist-info/METADATA
lp_mongodb-1.2.0.dist-info/WHEEL
lp_mongodb-1.2.0.dist-info/top_level.txt
lp_mongodb-1.2.0.dist-info/RECORD
