Metadata-Version: 2.1
Name: lp-mongodb
Version: 1.2.0
Summary: Thumbor thumbor lp adapters
Home-page: https://github.com/TechLaProvence/lp_mongodb
Author: TechLaProvence
Author-email: UNKNOWN
License: MIT
Keywords: thumbor mongodb mongo
Platform: UNKNOWN
Classifier: Development Status :: 5 - Production/Stable
Classifier: License :: OSI Approved :: MIT License
Classifier: Programming Language :: Python :: 2.7
Requires-Dist: thumbor (>=5.0.0)
Requires-Dist: pymongo
